micropidash/__init__.py
micropidash/micropidash.py
micropidash-1.0.0.dist-info/LICENSE
micropidash-1.0.0.dist-info/METADATA
micropidash-1.0.0.dist-info/WHEEL
micropidash-1.0.0.dist-info/top_level.txt
micropidash-1.0.0.dist-info/RECORD
