Metadata-Version: 2.1
Name: micropidash
Version: 1.0.0
Summary: A lightweight web dashboard for MicroPython (ESP32, Pico W)
Home-page: https://github.com/kritishmohapatra/micropidash
Author: Kritish Mohapatra
Author-email: kritishmohapatra06norisk@gmail.com
License: MIT
Classifier: Programming Language :: Python :: 3
Classifier: License :: OSI Approved :: MIT License
Classifier: Operating System :: OS Independent
License-File: LICENSE
